MANIFEST.in
README.rst
setup.py
lib/Saxon-HE-9.7.0-1.jar
lib/py4j-0.9.jar
lib/pyjxslt.jar
pyjxslt.egg-info/PKG-INFO
pyjxslt.egg-info/SOURCES.txt
pyjxslt.egg-info/dependency_links.txt
pyjxslt.egg-info/requires.txt
pyjxslt.egg-info/top_level.txt
pyjxslt.egg-info/zip-safe
scripts/pyjxslt
scripts/testgateway
src/__init__.py
src/pyjxslt/XSLTGateway.py
src/pyjxslt/XSLTLibrary.py
src/pyjxslt/__init__.py
src/pyjxslt/xsl/XMLToJson.xsl
static/xml/definitions.xml
tests/__init__.py
tests/testXSLTGateway.py
tests/testXSLTLibrary.py