Metadata-Version: 1.1
Name: pyjxslt
Version: 0.7.0
Summary: Python XSLT 2.0 Gateway
Home-page: http://github.com/CTS2/pyjxslt
Author: Harold Solbrig
Author-email: solbrig.harold@mayo.edu
License: BSD License
Platform: UNKNOWN
Classifier: Development Status :: 4 - Beta
Classifier: Intended Audience :: Developers
Classifier: License :: OSI Approved :: BSD License
Classifier: Programming Language :: Python
Classifier: Programming Language :: Python :: 3
Classifier: Programming Language :: Python :: 3 :: Only
Classifier: Topic :: Utilities
Classifier: Topic :: Text Processing
